valve_parsers/__init__.py
valve_parsers/constants.py
valve_parsers/pcf.py
valve_parsers/vpk.py
valve_parsers-1.1.0.dist-info/licenses/LICENSE
valve_parsers-1.1.0.dist-info/METADATA
valve_parsers-1.1.0.dist-info/WHEEL
valve_parsers-1.1.0.dist-info/top_level.txt
valve_parsers-1.1.0.dist-info/RECORD
