Metadata-Version: 2.4
Name: valve-parsers
Version: 1.1.0
Summary: Python library for parsing Valve game files (VPK and PCF)
Author: cueki
License: MIT
Project-URL: Homepage, https://github.com/cueki/valve-parsers
Project-URL: Repository, https://github.com/cueki/valve-parsers
Project-URL: Issues, https://github.com/cueki/valve-parsers/issues
Keywords: valve,vpk,pcf,particle,steam,source engine,team fortress,tf2,half-life,parser,archive,modding
Classifier: Development Status :: 4 - Beta
Classifier: Intended Audience :: Developers
Classifier: License :: OSI Approved :: MIT License
Classifier: Operating System :: OS Independent
Classifier: Programming Language :: Python :: 3
Classifier: Programming Language :: Python :: 3.8
Classifier: Programming Language :: Python :: 3.9
Classifier: Programming Language :: Python :: 3.10
Classifier: Programming Language :: Python :: 3.11
Classifier: Programming Language :: Python :: 3.12
Classifier: Topic :: Games/Entertainment
Classifier: Topic :: Software Development :: Libraries :: Python Modules
Classifier: Topic :: System :: Archiving
Requires-Python: >=3.8
License-File: LICENSE
Dynamic: license-file
